{
  "required": true,
  "package": "net.orandja.vw.mixin",
  "compatibilityLevel": "JAVA_16",
  "mixins": [
    "AbstractFurnaceBlockEntityMixin",
    "AbstractFurnaceBlockMixin",
    "AnimalEntityMixin",
    "BarrelBlockEntityMixin",
    "BarrelBlockMixin",
    "BatEntityMixin",
    "BrewingStandBlockEntityMixin",
    "BrewingStandBlockMixin",
    "BucketItemMixin",
    "ChestBlockEntityMixin",
    "ChestBlockMixin",
    "CropBlockMixin",
    "DamageTrackerMixin",
    "DispenserBlockEntityMixin",
    "DispenserBlockMixin",
    "EnchantmentMixin",
    "ExplosionMixin",
    "GrindstoneScreenHandlerMixin",
    "HandledScreenMixin",
    "HoeItemMixin",
    "HopperBlockEntityMixin",
    "HopperBlockMixin",
    "KelpPlantBlockMixin",
    "MobSpawnerLogicMixin",
    "PickaxeItemMixin",
    "PillarBlockMixin",
    "PlayerEntityMixin",
    "SchoolingFishEntityMixin",
    "ServerPlayerEntityMixin",
    "ServerWorldMixin",
    "ShapedRecipeSerializerMixin",
    "ShapelessRecipeSerializerMixin",
    "ShovelItemMixin",
    "ShulkerBoxBlockEntityMixin",
    "ShulkerBoxBlockMixin"
  ],
  "client": [
  ],
  "injectors": {
    "defaultRequire": 1
  }
}
